[
  {
    "id": "1",
    "type": "House",
    "title": "Cozy Family House",
    "description": "A beautiful family house with garden and garage.",
    "location": "Dhaka, Bangladesh",
    "ownerName": "Arif Rabbani",
    "email": "arif@example.com",
    "contactNumber": "+880123456789",
    "rentPrice": 25000,
    "availableFrom": "2025-09-10",
    "availableTo": "2026-09-10",
  "imageUrl": "https://images.unsplash.com/photo-1506744038136-46273834b3fb?auto=format&fit=crop&w=800&q=80",
  "latitude": 23.8103,
  "longitude": 90.4125
  },
  {
    "id": "2",
    "type": "Car",
    "title": "Toyota Corolla 2020",
    "description": "Well maintained car for city rides.",
    "location": "Chittagong, Bangladesh",
    "ownerName": "Mahmud Khan",
    "email": "mahmud@example.com",
    "contactNumber": "+880987654321",
    "rentPrice": 5000,
    "availableFrom": "2025-09-15",
    "availableTo": "2025-12-15",
  "imageUrl": "https://images.unsplash.com/photo-1511918984145-48de785d4c4e?auto=format&fit=crop&w=800&q=80",
  "latitude": 22.3569,
  "longitude": 91.7832
  },
  {
    "id": "3",
    "type": "Bike",
    "title": "Mountain Bike",
    "description": "Perfect for adventure and city commute.",
    "location": "Sylhet, Bangladesh",
    "ownerName": "Sinclaire White",
    "email": "sinclaire@example.com",
    "contactNumber": "+880112233445",
    "rentPrice": 1200,
    "availableFrom": "2025-09-20",
    "availableTo": "2026-01-20",
  "imageUrl": "https://images.unsplash.com/photo-1465101046530-73398c7f28ca?auto=format&fit=crop&w=800&q=80",
  "latitude": 24.9045,
  "longitude": 91.8611
  },
  {
    "id": "4",
    "type": "Garden",
    "title": "Urban Garden Space",
    "description": "Rent a green space for your events.",
    "location": "Khulna, Bangladesh",
    "ownerName": "Vercel Ahmed",
    "email": "vercel@example.com",
    "contactNumber": "+880998877665",
    "rentPrice": 8000,
    "availableFrom": "2025-10-01",
    "availableTo": "2026-03-01",
  "imageUrl": "https://images.unsplash.com/photo-1464983953574-0892a716854b?auto=format&fit=crop&w=800&q=80",
  "latitude": 22.8158,
  "longitude": 89.5683
  },
  {
    "id": "5",
    "type": "Laptop",
    "title": "MacBook Pro 2022",
    "description": "High-end laptop for work or study. 16GB RAM, M1 chip.",
    "location": "Barisal, Bangladesh",
    "ownerName": "Rafiul Islam",
    "email": "rafiul@example.com",
    "contactNumber": "+880123123123",
    "rentPrice": 3500,
    "availableFrom": "2025-09-12",
    "availableTo": "2025-12-12",
  "imageUrl": "https://images.unsplash.com/photo-1517336714731-489689fd1ca8?auto=format&fit=crop&w=800&q=80",
  "latitude": 22.7010,
  "longitude": 90.3535
  },
  {
    "id": "6",
    "type": "Camera",
    "title": "Canon EOS 80D DSLR",
    "description": "Professional camera for events and shoots.",
    "location": "Rajshahi, Bangladesh",
    "ownerName": "Shamim Hossain",
    "email": "shamim@example.com",
    "contactNumber": "+880321321321",
    "rentPrice": 2000,
    "availableFrom": "2025-09-18",
    "availableTo": "2026-01-18",
  "imageUrl": "https://images.unsplash.com/photo-1519125323398-675f0ddb6308?auto=format&fit=crop&w=800&q=80",
  "latitude": 24.3745,
  "longitude": 88.6042
  },
  {
    "id": "7",
    "type": "Office",
    "title": "Shared Office Space",
    "description": "Modern office space with internet and amenities.",
    "location": "Dhaka, Bangladesh",
    "ownerName": "Farhana Akter",
    "email": "farhana@example.com",
    "contactNumber": "+880456456456",
    "rentPrice": 12000,
    "availableFrom": "2025-09-25",
    "availableTo": "2026-09-25",
  "imageUrl": "https://images.unsplash.com/photo-1465101178521-c1a4c8a0a8b7?auto=format&fit=crop&w=800&q=80",
  "latitude": 23.8103,
  "longitude": 90.4125
  },
  {
    "id": "8",
    "type": "Event Hall",
    "title": "Grand Event Hall",
    "description": "Spacious hall for weddings, parties, and conferences.",
    "location": "Comilla, Bangladesh",
    "ownerName": "Jannat Ara",
    "email": "jannat@example.com",
    "contactNumber": "+880789789789",
    "rentPrice": 25000,
    "availableFrom": "2025-10-05",
    "availableTo": "2026-04-05",
  "imageUrl": "https://images.unsplash.com/photo-1509228468518-180dd4864904?auto=format&fit=crop&w=800&q=80",
  "latitude": 23.4614,
  "longitude": 91.1809
  }
]
